{
	"class" : {
		"numElements" : "ar 2/1/1999 21:22",
		"r:g:b:" : "das 7/6/2006 19:07",
		"r:g:b:a:" : "ar 2/7/1999 16:21",
		"red:green:blue:alpha:" : "ar 2/7/2006 17:33" },
	"instance" : {
		"a" : "das 11/30/2005 15:14",
		"alpha" : "das 11/30/2005 15:14",
		"alpha:" : "",
		"asColor" : "ar 5/4/2000 17:59",
		"asVector3" : "das 11/30/2005 15:14",
		"asVector4" : "jrd 11/3/2009 19:09",
		"asVectorColor" : "ar 2/7/2006 17:36",
		"b" : "das 11/30/2005 15:13",
		"blue" : "das 11/30/2005 15:13",
		"blue:" : "",
		"copyFrom:" : "das 7/10/2006 09:58",
		"g" : "das 11/30/2005 15:13",
		"green" : "das 11/30/2005 15:13",
		"green:" : "",
		"interpolateTo:at:" : "ar 2/7/2006 17:33",
		"isZero" : "ar 2/15/1999 22:12",
		"pixelValue32" : "ar 2/4/1999 20:21",
		"privateLoadFrom:" : "ar 2/15/1999 22:12",
		"r" : "das 11/30/2005 15:13",
		"r:g:b:a:" : "ar 2/7/1999 16:21",
		"red" : "das 11/30/2005 15:13",
		"red:" : "" } }
