{
	"class" : {
		 },
	"instance" : {
		"accept" : "ar 6/16/2003 23:37",
		"action" : "ar 8/20/2002 02:09",
		"action:" : "ar 8/20/2002 02:09",
		"brush" : "ar 8/20/2002 02:10",
		"brush:" : "ar 8/20/2002 02:10",
		"cancel" : "ar 10/12/2002 23:48",
		"cancelPainting:evt:" : "ar 8/20/2002 13:35",
		"clear" : "ar 8/20/2002 02:24",
		"clearPainting:" : "ar 8/20/2002 02:05",
		"drawOn:" : "ar 8/20/2002 02:01",
		"erase:" : "ar 8/20/2002 02:03",
		"erasePrep:" : "ar 8/20/2002 02:17",
		"fill:" : "ar 6/19/2003 23:21",
		"handlesMouseDown:" : "ar 8/20/2002 02:01",
		"handlesMouseOver:" : "ar 8/20/2002 02:02",
		"handlesMouseOverDragging:" : "ar 8/20/2002 02:02",
		"lastEvent" : "ar 8/20/2002 02:10",
		"lastEvent:" : "ar 8/20/2002 02:09",
		"mouseDown:" : "ar 8/20/2002 02:20",
		"mouseEnter:" : "ar 8/20/2002 02:40",
		"mouseEnterDragging:" : "ar 8/20/2002 02:01",
		"mouseLeave:" : "ar 8/20/2002 02:01",
		"mouseLeaveDragging:" : "ar 8/20/2002 02:02",
		"mouseMove:" : "ar 8/20/2002 02:15",
		"mouseUp:" : "ar 8/20/2002 02:18",
		"paint:" : "ar 9/19/2002 15:59",
		"paintBoxChanged:" : "ar 8/20/2002 02:31",
		"paintingForm" : "ar 6/17/2003 00:51",
		"paintingFormPen" : "ar 8/20/2002 02:08",
		"paintingFormPen:" : "ar 8/20/2002 02:08",
		"palette" : "ar 8/20/2002 02:02",
		"paletteAttached:" : "ar 8/20/2002 02:14",
		"paletteDetached:" : "ar 8/20/2002 02:06",
		"prepareToPaint:" : "ar 8/20/2002 02:22",
		"repaint:" : "ar 6/17/2003 00:05",
		"savePainting:evt:" : "ar 8/20/2002 13:35",
		"teapot" : "ar 8/20/2002 13:38",
		"teapot:" : "ar 8/20/2002 13:38",
		"undo:" : "ar 8/20/2002 02:11",
		"undoPainting:evt:" : "ar 8/20/2002 02:06" } }
